[
  {
    "match": "卡塔尔 vs 厄瓜多尔",
    "date": "2022-11-20",
    "stage": "group",
    "score": "0-2",
    "direction": "away",
    "actual": "away",
    "pinnacle_close": "3.84/3.18/2.24",
    "deVig": "25.5%/30.8%/43.7%",
    "fav_odds": "2.26",
    "fvs_score": 0,
    "fvs_triggers": "-",
    "drm_score": 2,
    "drm_triggers": "DRM-1(+2)",
    "lottery_ev": "-29.9%",
    "fvs_drm_verdict": "⚠️中平局",
    "vetoed": true,
    "veto_reason": "EV-30%",
    "old_correct": true,
    "new_correct": false
  },
  {
    "match": "塞内加尔 vs 荷兰",
    "date": "2022-11-21",
    "stage": "group",
    "score": "0-2",
    "direction": "away",
    "actual": "away",
    "pinnacle_close": "6.26/3.70/1.68",
    "deVig": "15.6%/26.4%/58.1%",
    "fav_odds": "1.66",
    "fvs_score": 1,
    "fvs_triggers": "FVS-7(+1)",
    "drm_score": 1,
    "drm_triggers": "DRM-1(+1)",
    "lottery_ev": "-31.7%",
    "fvs_drm_verdict": "正常",
    "vetoed": true,
    "veto_reason": "EV-32%",
    "old_correct": true,
    "new_correct": false
  },
  {
    "match": "英格兰 vs 伊朗",
    "date": "2022-11-21",
    "stage": "group",
    "score": "6-2",
    "direction": "home",
    "actual": "home",
    "pinnacle_close": "1.38/4.65/11.50",
    "deVig": "70.6%/20.9%/8.5%",
    "fav_odds": "1.35",
    "fvs_score": 2,
    "fvs_triggers": "FVS-11(+2)",
    "drm_score": 0,
    "drm_triggers": "-",
    "lottery_ev": "-32.2%",
    "fvs_drm_verdict": "⚠️衰减",
    "vetoed": true,
    "veto_reason": "EV-32%",
    "old_correct": true,
    "new_correct": false
  },
  {
    "match": "美国 vs 威尔士",
    "date": "2022-11-22",
    "stage": "group",
    "score": "1-1",
    "direction": "home",
    "actual": "draw",
    "pinnacle_close": "2.54/3.14/3.23",
    "deVig": "38.5%/31.2%/30.3%",
    "fav_odds": "2.46",
    "fvs_score": 0,
    "fvs_triggers": "-",
    "drm_score": 2,
    "drm_triggers": "DRM-1(+2)",
    "lottery_ev": "-32.8%",
    "fvs_drm_verdict": "⚠️中平局",
    "vetoed": true,
    "veto_reason": "EV-33%",
    "old_correct": false,
    "new_correct": false
  },
  {
    "match": "墨西哥 vs 波兰",
    "date": "2022-11-22",
    "stage": "group",
    "score": "0-0",
    "direction": "home",
    "actual": "draw",
    "pinnacle_close": "2.48/3.19/3.27",
    "deVig": "39.4%/30.7%/29.9%",
    "fav_odds": "2.47",
    "fvs_score": 0,
    "fvs_triggers": "-",
    "drm_score": 2,
    "drm_triggers": "DRM-1(+2)",
    "lottery_ev": "-30.9%",
    "fvs_drm_verdict": "⚠️中平局",
    "vetoed": true,
    "veto_reason": "EV-31%",
    "old_correct": false,
    "new_correct": false
  },
  {
    "match": "阿根廷 vs 沙特",
    "date": "2022-11-22",
    "stage": "group",
    "score": "1-2",
    "direction": "home",
    "actual": "away",
    "pinnacle_close": "1.13/10.50/22.00",
    "deVig": "86.3%/9.3%/4.4%",
    "fav_odds": "1.12",
    "fvs_score": 2,
    "fvs_triggers": "FVS-1(+2)",
    "drm_score": 0,
    "drm_triggers": "-",
    "lottery_ev": "-31.4%",
    "fvs_drm_verdict": "⚠️衰减",
    "vetoed": true,
    "veto_reason": "EV-31%",
    "old_correct": false,
    "new_correct": false
  },
  {
    "match": "丹麦 vs 突尼斯",
    "date": "2022-11-22",
    "stage": "group",
    "score": "0-0",
    "direction": "home",
    "actual": "draw",
    "pinnacle_close": "1.61/3.94/6.70",
    "deVig": "60.6%/24.8%/14.6%",
    "fav_odds": "1.57",
    "fvs_score": 0,
    "fvs_triggers": "-",
    "drm_score": 0,
    "drm_triggers": "-",
    "lottery_ev": "-32.2%",
    "fvs_drm_verdict": "正常",
    "vetoed": true,
    "veto_reason": "EV-32%",
    "old_correct": false,
    "new_correct": false
  },
  {
    "match": "法国 vs 澳大利亚",
    "date": "2022-11-23",
    "stage": "group",
    "score": "4-1",
    "direction": "home",
    "actual": "home",
    "pinnacle_close": "1.22/7.50/15.50",
    "deVig": "80.6%/13.1%/6.3%",
    "fav_odds": "1.22",
    "fvs_score": 2,
    "fvs_triggers": "FVS-1(+1),FVS-3(+1)",
    "drm_score": 0,
    "drm_triggers": "-",
    "lottery_ev": "-30.4%",
    "fvs_drm_verdict": "⚠️衰减",
    "vetoed": true,
    "veto_reason": "EV-30%",
    "old_correct": true,
    "new_correct": false
  },
  {
    "match": "西班牙 vs 哥斯达黎加",
    "date": "2022-11-23",
    "stage": "group",
    "score": "7-0",
    "direction": "home",
    "actual": "home",
    "pinnacle_close": "1.15/9.15/21.00",
    "deVig": "84.7%/10.6%/4.6%",
    "fav_odds": "1.16",
    "fvs_score": 3,
    "fvs_triggers": "FVS-1(+2),FVS-3(+1)",
    "drm_score": 0,
    "drm_triggers": "-",
    "lottery_ev": "-30.3%",
    "fvs_drm_verdict": "⚠️衰减",
    "vetoed": true,
    "veto_reason": "EV-30%",
    "old_correct": true,
    "new_correct": false
  },
  {
    "match": "德国 vs 日本",
    "date": "2022-11-23",
    "stage": "group",
    "score": "1-2",
    "direction": "home",
    "actual": "away",
    "pinnacle_close": "1.46/4.95/7.30",
    "deVig": "66.9%/19.7%/13.4%",
    "fav_odds": "1.42",
    "fvs_score": 3,
    "fvs_triggers": "FVS-3(+1),FVS-11(+2)",
    "drm_score": 0,
    "drm_triggers": "-",
    "lottery_ev": "-32.6%",
    "fvs_drm_verdict": "⚠️衰减",
    "vetoed": true,
    "veto_reason": "EV-33%",
    "old_correct": false,
    "new_correct": false
  },
  {
    "match": "摩洛哥 vs 克罗地亚",
    "date": "2022-11-23",
    "stage": "group",
    "score": "0-0",
    "direction": "away",
    "actual": "draw",
    "pinnacle_close": "3.55/3.29/2.30",
    "deVig": "27.6%/29.8%/42.6%",
    "fav_odds": "2.19",
    "fvs_score": 1,
    "fvs_triggers": "FVS-3(+1)",
    "drm_score": 2,
    "drm_triggers": "DRM-1(+2)",
    "lottery_ev": "-33.7%",
    "fvs_drm_verdict": "⚠️中平局",
    "vetoed": true,
    "veto_reason": "EV-34%",
    "old_correct": false,
    "new_correct": false
  },
  {
    "match": "比利时 vs 加拿大",
    "date": "2022-11-24",
    "stage": "group",
    "score": "1-0",
    "direction": "home",
    "actual": "home",
    "pinnacle_close": "1.64/4.20/5.62",
    "deVig": "59.4%/23.2%/17.3%",
    "fav_odds": "1.55",
    "fvs_score": 0,
    "fvs_triggers": "-",
    "drm_score": 0,
    "drm_triggers": "-",
    "lottery_ev": "-34.7%",
    "fvs_drm_verdict": "正常",
    "vetoed": true,
    "veto_reason": "EV-35%",
    "old_correct": true,
    "new_correct": false
  },
  {
    "match": "瑞士 vs 喀麦隆",
    "date": "2022-11-24",
    "stage": "group",
    "score": "1-0",
    "direction": "home",
    "actual": "home",
    "pinnacle_close": "1.80/3.60/5.34",
    "deVig": "54.4%/27.2%/18.3%",
    "fav_odds": "1.80",
    "fvs_score": 0,
    "fvs_triggers": "-",
    "drm_score": 1,
    "drm_triggers": "DRM-1(+1)",
    "lottery_ev": "-30.3%",
    "fvs_drm_verdict": "正常",
    "vetoed": true,
    "veto_reason": "EV-30%",
    "old_correct": true,
    "new_correct": false
  },
  {
    "match": "葡萄牙 vs 加纳",
    "date": "2022-11-24",
    "stage": "group",
    "score": "3-2",
    "direction": "home",
    "actual": "home",
    "pinnacle_close": "1.31/5.75/10.80",
    "deVig": "74.1%/16.9%/9.0%",
    "fav_odds": "1.30",
    "fvs_score": 0,
    "fvs_triggers": "-",
    "drm_score": 0,
    "drm_triggers": "-",
    "lottery_ev": "-31.4%",
    "fvs_drm_verdict": "正常",
    "vetoed": true,
    "veto_reason": "EV-31%",
    "old_correct": true,
    "new_correct": false
  },
  {
    "match": "乌拉圭 vs 韩国",
    "date": "2022-11-24",
    "stage": "group",
    "score": "0-0",
    "direction": "home",
    "actual": "draw",
    "pinnacle_close": "1.81/3.60/5.26",
    "deVig": "54.1%/27.2%/18.6%",
    "fav_odds": "1.77",
    "fvs_score": 1,
    "fvs_triggers": "FVS-7(+1)",
    "drm_score": 1,
    "drm_triggers": "DRM-1(+1)",
    "lottery_ev": "-32.1%",
    "fvs_drm_verdict": "正常",
    "vetoed": true,
    "veto_reason": "EV-32%",
    "old_correct": false,
    "new_correct": false
  },
  {
    "match": "荷兰 vs 厄瓜多尔",
    "date": "2022-11-25",
    "stage": "group",
    "score": "1-1",
    "direction": "home",
    "actual": "draw",
    "pinnacle_close": "1.89/3.44/4.99",
    "deVig": "51.9%/28.5%/19.6%",
    "fav_odds": "1.83",
    "fvs_score": 0,
    "fvs_triggers": "-",
    "drm_score": 2,
    "drm_triggers": "DRM-1(+2)",
    "lottery_ev": "-32.5%",
    "fvs_drm_verdict": "⚠️中平局",
    "vetoed": true,
    "veto_reason": "EV-33%",
    "old_correct": false,
    "new_correct": false
  },
  {
    "match": "卡塔尔 vs 塞内加尔",
    "date": "2022-11-25",
    "stage": "group",
    "score": "1-3",
    "direction": "away",
    "actual": "away",
    "pinnacle_close": "5.53/3.67/1.76",
    "deVig": "17.7%/26.7%/55.6%",
    "fav_odds": "1.73",
    "fvs_score": 1,
    "fvs_triggers": "FVS-7(+1)",
    "drm_score": 1,
    "drm_triggers": "DRM-1(+1)",
    "lottery_ev": "-31.9%",
    "fvs_drm_verdict": "正常",
    "vetoed": true,
    "veto_reason": "EV-32%",
    "old_correct": true,
    "new_correct": false
  },
  {
    "match": "威尔士 vs 伊朗",
    "date": "2022-11-25",
    "stage": "group",
    "score": "0-2",
    "direction": "home",
    "actual": "away",
    "pinnacle_close": "2.20/3.21/3.96",
    "deVig": "44.6%/30.6%/24.8%",
    "fav_odds": "2.14",
    "fvs_score": 0,
    "fvs_triggers": "-",
    "drm_score": 2,
    "drm_triggers": "DRM-1(+2)",
    "lottery_ev": "-32.3%",
    "fvs_drm_verdict": "⚠️中平局",
    "vetoed": true,
    "veto_reason": "EV-32%",
    "old_correct": false,
    "new_correct": false
  },
  {
    "match": "巴西 vs 塞尔维亚",
    "date": "2022-11-25",
    "stage": "group",
    "score": "2-0",
    "direction": "home",
    "actual": "home",
    "pinnacle_close": "1.51/4.65/6.90",
    "deVig": "64.8%/21.0%/14.2%",
    "fav_odds": "1.44",
    "fvs_score": 2,
    "fvs_triggers": "FVS-11(+2)",
    "drm_score": 0,
    "drm_triggers": "-",
    "lottery_ev": "-33.7%",
    "fvs_drm_verdict": "⚠️衰减",
    "vetoed": true,
    "veto_reason": "EV-34%",
    "old_correct": true,
    "new_correct": false
  },
  {
    "match": "英格兰 vs 美国",
    "date": "2022-11-26",
    "stage": "group",
    "score": "0-0",
    "direction": "home",
    "actual": "draw",
    "pinnacle_close": "1.50/4.35/7.95",
    "deVig": "65.2%/22.5%/12.3%",
    "fav_odds": "1.48",
    "fvs_score": 0,
    "fvs_triggers": "-",
    "drm_score": 0,
    "drm_triggers": "-",
    "lottery_ev": "-31.5%",
    "fvs_drm_verdict": "正常",
    "vetoed": true,
    "veto_reason": "EV-31%",
    "old_correct": false,
    "new_correct": false
  },
  {
    "match": "波兰 vs 沙特",
    "date": "2022-11-26",
    "stage": "group",
    "score": "2-0",
    "direction": "home",
    "actual": "home",
    "pinnacle_close": "1.73/3.75/5.70",
    "deVig": "56.7%/26.1%/17.2%",
    "fav_odds": "1.72",
    "fvs_score": 1,
    "fvs_triggers": "FVS-7(+1)",
    "drm_score": 1,
    "drm_triggers": "DRM-1(+1)",
    "lottery_ev": "-30.7%",
    "fvs_drm_verdict": "正常",
    "vetoed": true,
    "veto_reason": "EV-31%",
    "old_correct": true,
    "new_correct": false
  },
  {
    "match": "法国 vs 丹麦",
    "date": "2022-11-26",
    "stage": "group",
    "score": "2-1",
    "direction": "home",
    "actual": "home",
    "pinnacle_close": "1.85/3.61/4.92",
    "deVig": "53.0%/27.1%/19.9%",
    "fav_odds": "1.82",
    "fvs_score": 0,
    "fvs_triggers": "-",
    "drm_score": 1,
    "drm_triggers": "DRM-1(+1)",
    "lottery_ev": "-31.4%",
    "fvs_drm_verdict": "正常",
    "vetoed": true,
    "veto_reason": "EV-31%",
    "old_correct": true,
    "new_correct": false
  },
  {
    "match": "突尼斯 vs 澳大利亚",
    "date": "2022-11-26",
    "stage": "group",
    "score": "0-1",
    "direction": "home",
    "actual": "away",
    "pinnacle_close": "2.23/3.46/3.54",
    "deVig": "44.0%/28.3%/27.7%",
    "fav_odds": "2.19",
    "fvs_score": 0,
    "fvs_triggers": "-",
    "drm_score": 2,
    "drm_triggers": "DRM-1(+2)",
    "lottery_ev": "-31.6%",
    "fvs_drm_verdict": "⚠️中平局",
    "vetoed": true,
    "veto_reason": "EV-32%",
    "old_correct": false,
    "new_correct": false
  },
  {
    "match": "阿根廷 vs 墨西哥",
    "date": "2022-11-27",
    "stage": "group",
    "score": "2-0",
    "direction": "home",
    "actual": "home",
    "pinnacle_close": "1.61/4.00/6.50",
    "deVig": "60.6%/24.4%/15.0%",
    "fav_odds": "1.53",
    "fvs_score": 0,
    "fvs_triggers": "-",
    "drm_score": 0,
    "drm_triggers": "-",
    "lottery_ev": "-34.1%",
    "fvs_drm_verdict": "正常",
    "vetoed": true,
    "veto_reason": "EV-34%",
    "old_correct": true,
    "new_correct": false
  },
  {
    "match": "日本 vs 哥斯达黎加",
    "date": "2022-11-27",
    "stage": "group",
    "score": "0-1",
    "direction": "home",
    "actual": "away",
    "pinnacle_close": "1.50/4.40/7.75",
    "deVig": "65.2%/22.2%/12.6%",
    "fav_odds": "1.51",
    "fvs_score": 0,
    "fvs_triggers": "-",
    "drm_score": 0,
    "drm_triggers": "-",
    "lottery_ev": "-30.3%",
    "fvs_drm_verdict": "正常",
    "vetoed": true,
    "veto_reason": "EV-30%",
    "old_correct": false,
    "new_correct": false
  },
  {
    "match": "克罗地亚 vs 加拿大",
    "date": "2022-11-27",
    "stage": "group",
    "score": "4-1",
    "direction": "home",
    "actual": "home",
    "pinnacle_close": "2.28/3.36/3.54",
    "deVig": "43.1%/29.2%/27.7%",
    "fav_odds": "2.19",
    "fvs_score": 0,
    "fvs_triggers": "-",
    "drm_score": 2,
    "drm_triggers": "DRM-1(+2)",
    "lottery_ev": "-33.1%",
    "fvs_drm_verdict": "⚠️中平局",
    "vetoed": true,
    "veto_reason": "EV-33%",
    "old_correct": true,
    "new_correct": false
  },
  {
    "match": "比利时 vs 摩洛哥",
    "date": "2022-11-27",
    "stage": "group",
    "score": "0-2",
    "direction": "home",
    "actual": "away",
    "pinnacle_close": "1.91/3.50/4.75",
    "deVig": "51.3%/28.0%/20.6%",
    "fav_odds": "1.86",
    "fvs_score": 0,
    "fvs_triggers": "-",
    "drm_score": 2,
    "drm_triggers": "DRM-1(+2)",
    "lottery_ev": "-32.0%",
    "fvs_drm_verdict": "⚠️中平局",
    "vetoed": true,
    "veto_reason": "EV-32%",
    "old_correct": false,
    "new_correct": false
  },
  {
    "match": "西班牙 vs 德国",
    "date": "2022-11-28",
    "stage": "group",
    "score": "1-1",
    "direction": "home",
    "actual": "draw",
    "pinnacle_close": "2.59/3.43/2.92",
    "deVig": "37.8%/28.6%/33.6%",
    "fav_odds": "2.50",
    "fvs_score": 0,
    "fvs_triggers": "-",
    "drm_score": 2,
    "drm_triggers": "DRM-1(+2)",
    "lottery_ev": "-32.9%",
    "fvs_drm_verdict": "⚠️中平局",
    "vetoed": true,
    "veto_reason": "EV-33%",
    "old_correct": false,
    "new_correct": false
  },
  {
    "match": "巴西 vs 瑞士",
    "date": "2022-11-28",
    "stage": "group",
    "score": "1-0",
    "direction": "home",
    "actual": "home",
    "pinnacle_close": "1.51/4.35/8.00",
    "deVig": "65.1%/22.6%/12.3%",
    "fav_odds": "1.47",
    "fvs_score": 0,
    "fvs_triggers": "-",
    "drm_score": 0,
    "drm_triggers": "-",
    "lottery_ev": "-32.0%",
    "fvs_drm_verdict": "正常",
    "vetoed": true,
    "veto_reason": "EV-32%",
    "old_correct": true,
    "new_correct": false
  },
  {
    "match": "喀麦隆 vs 塞尔维亚",
    "date": "2022-11-28",
    "stage": "group",
    "score": "3-3",
    "direction": "away",
    "actual": "draw",
    "pinnacle_close": "5.60/3.95/1.69",
    "deVig": "17.4%/24.7%/57.8%",
    "fav_odds": "1.73",
    "fvs_score": 0,
    "fvs_triggers": "-",
    "drm_score": 0,
    "drm_triggers": "-",
    "lottery_ev": "-29.1%",
    "fvs_drm_verdict": "正常",
    "vetoed": true,
    "veto_reason": "EV-29%",
    "old_correct": false,
    "new_correct": false
  },
  {
    "match": "韩国 vs 加纳",
    "date": "2022-11-28",
    "stage": "group",
    "score": "2-3",
    "direction": "home",
    "actual": "away",
    "pinnacle_close": "2.78/3.16/2.93",
    "deVig": "35.4%/31.1%/33.5%",
    "fav_odds": "2.68",
    "fvs_score": 0,
    "fvs_triggers": "-",
    "drm_score": 2,
    "drm_triggers": "DRM-1(+2)",
    "lottery_ev": "-32.7%",
    "fvs_drm_verdict": "⚠️中平局",
    "vetoed": true,
    "veto_reason": "EV-33%",
    "old_correct": false,
    "new_correct": false
  },
  {
    "match": "卡塔尔 vs 荷兰",
    "date": "2022-11-29",
    "stage": "group",
    "score": "0-2",
    "direction": "away",
    "actual": "away",
    "pinnacle_close": "23.32/7.18/1.18",
    "deVig": "4.2%/13.5%/82.3%",
    "fav_odds": "1.20",
    "fvs_score": 3,
    "fvs_triggers": "FVS-1(+1),FVS-11(+2)",
    "drm_score": 0,
    "drm_triggers": "-",
    "lottery_ev": "-29.9%",
    "fvs_drm_verdict": "⚠️衰减",
    "vetoed": true,
    "veto_reason": "EV-30%",
    "old_correct": true,
    "new_correct": false
  },
  {
    "match": "厄瓜多尔 vs 塞内加尔",
    "date": "2022-11-29",
    "stage": "group",
    "score": "1-2",
    "direction": "home",
    "actual": "away",
    "pinnacle_close": "2.43/3.29/3.20",
    "deVig": "40.0%/29.6%/30.4%",
    "fav_odds": "2.43",
    "fvs_score": 0,
    "fvs_triggers": "-",
    "drm_score": 2,
    "drm_triggers": "DRM-1(+2)",
    "lottery_ev": "-30.8%",
    "fvs_drm_verdict": "⚠️中平局",
    "vetoed": true,
    "veto_reason": "EV-31%",
    "old_correct": false,
    "new_correct": false
  },
  {
    "match": "葡萄牙 vs 乌拉圭",
    "date": "2022-11-29",
    "stage": "group",
    "score": "2-0",
    "direction": "home",
    "actual": "home",
    "pinnacle_close": "1.94/3.41/4.69",
    "deVig": "50.4%/28.7%/20.9%",
    "fav_odds": "1.95",
    "fvs_score": 0,
    "fvs_triggers": "-",
    "drm_score": 2,
    "drm_triggers": "DRM-1(+2)",
    "lottery_ev": "-30.3%",
    "fvs_drm_verdict": "⚠️中平局",
    "vetoed": true,
    "veto_reason": "EV-30%",
    "old_correct": true,
    "new_correct": false
  },
  {
    "match": "伊朗 vs 美国",
    "date": "2022-11-30",
    "stage": "group",
    "score": "0-1",
    "direction": "away",
    "actual": "away",
    "pinnacle_close": "4.52/3.52/1.92",
    "deVig": "21.6%/27.7%/50.8%",
    "fav_odds": "1.95",
    "fvs_score": 1,
    "fvs_triggers": "FVS-3(+1)",
    "drm_score": 1,
    "drm_triggers": "DRM-1(+1)",
    "lottery_ev": "-29.8%",
    "fvs_drm_verdict": "正常",
    "vetoed": true,
    "veto_reason": "EV-30%",
    "old_correct": true,
    "new_correct": false
  },
  {
    "match": "威尔士 vs 英格兰",
    "date": "2022-11-30",
    "stage": "group",
    "score": "0-3",
    "direction": "away",
    "actual": "away",
    "pinnacle_close": "8.56/4.53/1.45",
    "deVig": "11.4%/21.5%/67.1%",
    "fav_odds": "1.43",
    "fvs_score": 3,
    "fvs_triggers": "FVS-3(+1),FVS-11(+2)",
    "drm_score": 0,
    "drm_triggers": "-",
    "lottery_ev": "-32.1%",
    "fvs_drm_verdict": "⚠️衰减",
    "vetoed": true,
    "veto_reason": "EV-32%",
    "old_correct": true,
    "new_correct": false
  },
  {
    "match": "突尼斯 vs 法国",
    "date": "2022-11-30",
    "stage": "group",
    "score": "1-0",
    "direction": "away",
    "actual": "home",
    "pinnacle_close": "5.80/4.00/1.63",
    "deVig": "16.6%/24.1%/59.2%",
    "fav_odds": "1.57",
    "fvs_score": 1,
    "fvs_triggers": "FVS-3(+1)",
    "drm_score": 0,
    "drm_triggers": "-",
    "lottery_ev": "-33.8%",
    "fvs_drm_verdict": "正常",
    "vetoed": true,
    "veto_reason": "EV-34%",
    "old_correct": false,
    "new_correct": false
  },
  {
    "match": "澳大利亚 vs 丹麦",
    "date": "2022-11-30",
    "stage": "group",
    "score": "1-0",
    "direction": "away",
    "actual": "home",
    "pinnacle_close": "7.50/5.10/1.44",
    "deVig": "13.0%/19.2%/67.8%",
    "fav_odds": "1.44",
    "fvs_score": 3,
    "fvs_triggers": "FVS-3(+1),FVS-11(+2)",
    "drm_score": 0,
    "drm_triggers": "-",
    "lottery_ev": "-30.6%",
    "fvs_drm_verdict": "⚠️衰减",
    "vetoed": true,
    "veto_reason": "EV-31%",
    "old_correct": false,
    "new_correct": false
  },
  {
    "match": "沙特 vs 墨西哥",
    "date": "2022-12-01",
    "stage": "group",
    "score": "1-2",
    "direction": "away",
    "actual": "away",
    "pinnacle_close": "5.50/4.40/1.63",
    "deVig": "17.8%/22.2%/60.0%",
    "fav_odds": "1.60",
    "fvs_score": 0,
    "fvs_triggers": "-",
    "drm_score": 0,
    "drm_triggers": "-",
    "lottery_ev": "-31.7%",
    "fvs_drm_verdict": "正常",
    "vetoed": true,
    "veto_reason": "EV-32%",
    "old_correct": true,
    "new_correct": false
  },
  {
    "match": "波兰 vs 阿根廷",
    "date": "2022-12-01",
    "stage": "group",
    "score": "0-2",
    "direction": "away",
    "actual": "away",
    "pinnacle_close": "8.40/4.70/1.44",
    "deVig": "11.6%/20.7%/67.7%",
    "fav_odds": "1.43",
    "fvs_score": 2,
    "fvs_triggers": "FVS-11(+2)",
    "drm_score": 0,
    "drm_triggers": "-",
    "lottery_ev": "-31.4%",
    "fvs_drm_verdict": "⚠️衰减",
    "vetoed": true,
    "veto_reason": "EV-31%",
    "old_correct": true,
    "new_correct": false
  },
  {
    "match": "克罗地亚 vs 比利时",
    "date": "2022-12-01",
    "stage": "group",
    "score": "0-0",
    "direction": "away",
    "actual": "draw",
    "pinnacle_close": "3.17/3.46/2.42",
    "deVig": "31.0%/28.4%/40.6%",
    "fav_odds": "2.38",
    "fvs_score": 0,
    "fvs_triggers": "-",
    "drm_score": 2,
    "drm_triggers": "DRM-1(+2)",
    "lottery_ev": "-31.4%",
    "fvs_drm_verdict": "⚠️中平局",
    "vetoed": true,
    "veto_reason": "EV-31%",
    "old_correct": false,
    "new_correct": false
  },
  {
    "match": "加拿大 vs 摩洛哥",
    "date": "2022-12-01",
    "stage": "group",
    "score": "1-2",
    "direction": "away",
    "actual": "away",
    "pinnacle_close": "4.79/3.54/1.88",
    "deVig": "20.4%/27.6%/52.0%",
    "fav_odds": "1.85",
    "fvs_score": 0,
    "fvs_triggers": "-",
    "drm_score": 1,
    "drm_triggers": "DRM-1(+1)",
    "lottery_ev": "-31.6%",
    "fvs_drm_verdict": "正常",
    "vetoed": true,
    "veto_reason": "EV-32%",
    "old_correct": true,
    "new_correct": false
  },
  {
    "match": "哥斯达黎加 vs 德国",
    "date": "2022-12-02",
    "stage": "group",
    "score": "2-4",
    "direction": "away",
    "actual": "away",
    "pinnacle_close": "21.00/11.50/1.12",
    "deVig": "4.6%/8.5%/86.9%",
    "fav_odds": "1.10",
    "fvs_score": 4,
    "fvs_triggers": "FVS-1(+2),FVS-11(+2)",
    "drm_score": 0,
    "drm_triggers": "-",
    "lottery_ev": "-31.9%",
    "fvs_drm_verdict": "🔴严重",
    "vetoed": true,
    "veto_reason": "FVS-4,EV-32%",
    "old_correct": true,
    "new_correct": false
  },
  {
    "match": "日本 vs 西班牙",
    "date": "2022-12-02",
    "stage": "group",
    "score": "2-1",
    "direction": "away",
    "actual": "home",
    "pinnacle_close": "6.57/4.41/1.56",
    "deVig": "14.9%/22.2%/62.8%",
    "fav_odds": "1.45",
    "fvs_score": 0,
    "fvs_triggers": "-",
    "drm_score": 0,
    "drm_triggers": "-",
    "lottery_ev": "-35.3%",
    "fvs_drm_verdict": "正常",
    "vetoed": true,
    "veto_reason": "EV-35%",
    "old_correct": false,
    "new_correct": false
  },
  {
    "match": "加纳 vs 乌拉圭",
    "date": "2022-12-02",
    "stage": "group",
    "score": "0-2",
    "direction": "away",
    "actual": "away",
    "pinnacle_close": "4.93/3.99/1.76",
    "deVig": "19.9%/24.5%/55.6%",
    "fav_odds": "1.78",
    "fvs_score": 0,
    "fvs_triggers": "-",
    "drm_score": 0,
    "drm_triggers": "-",
    "lottery_ev": "-29.8%",
    "fvs_drm_verdict": "正常",
    "vetoed": true,
    "veto_reason": "EV-30%",
    "old_correct": true,
    "new_correct": false
  },
  {
    "match": "韩国 vs 葡萄牙",
    "date": "2022-12-02",
    "stage": "group",
    "score": "2-1",
    "direction": "away",
    "actual": "home",
    "pinnacle_close": "4.37/3.87/1.86",
    "deVig": "22.3%/25.2%/52.5%",
    "fav_odds": "1.82",
    "fvs_score": 0,
    "fvs_triggers": "-",
    "drm_score": 1,
    "drm_triggers": "DRM-1(+1)",
    "lottery_ev": "-32.3%",
    "fvs_drm_verdict": "正常",
    "vetoed": true,
    "veto_reason": "EV-32%",
    "old_correct": false,
    "new_correct": false
  },
  {
    "match": "塞尔维亚 vs 瑞士",
    "date": "2022-12-03",
    "stage": "group",
    "score": "2-3",
    "direction": "home",
    "actual": "away",
    "pinnacle_close": "2.54/3.54/2.92",
    "deVig": "38.6%/27.7%/33.6%",
    "fav_odds": "2.56",
    "fvs_score": 0,
    "fvs_triggers": "-",
    "drm_score": 1,
    "drm_triggers": "DRM-1(+1)",
    "lottery_ev": "-29.6%",
    "fvs_drm_verdict": "正常",
    "vetoed": true,
    "veto_reason": "EV-30%",
    "old_correct": false,
    "new_correct": false
  },
  {
    "match": "喀麦隆 vs 巴西",
    "date": "2022-12-03",
    "stage": "group",
    "score": "1-0",
    "direction": "away",
    "actual": "home",
    "pinnacle_close": "8.75/5.50/1.36",
    "deVig": "11.1%/17.6%/71.3%",
    "fav_odds": "1.35",
    "fvs_score": 0,
    "fvs_triggers": "-",
    "drm_score": 0,
    "drm_triggers": "-",
    "lottery_ev": "-31.8%",
    "fvs_drm_verdict": "正常",
    "vetoed": true,
    "veto_reason": "EV-32%",
    "old_correct": false,
    "new_correct": false
  },
  {
    "match": "荷兰 vs 美国",
    "date": "2022-12-03",
    "stage": "round_of_16",
    "score": "3-1",
    "direction": "home",
    "actual": "home",
    "pinnacle_close": "1.95/3.44/4.60",
    "deVig": "50.2%/28.5%/21.3%",
    "fav_odds": "1.93",
    "fvs_score": 0,
    "fvs_triggers": "-",
    "drm_score": 2,
    "drm_triggers": "DRM-1(+2)",
    "lottery_ev": "-31.1%",
    "fvs_drm_verdict": "⚠️中平局",
    "vetoed": true,
    "veto_reason": "EV-31%",
    "old_correct": true,
    "new_correct": false
  },
  {
    "match": "阿根廷 vs 澳大利亚",
    "date": "2022-12-04",
    "stage": "round_of_16",
    "score": "2-1",
    "direction": "home",
    "actual": "home",
    "pinnacle_close": "1.30/6.90/9.25",
    "deVig": "75.2%/14.2%/10.6%",
    "fav_odds": "1.27",
    "fvs_score": 5,
    "fvs_triggers": "FVS-2(+2系统),FVS-3(+1),FVS-11(+2)",
    "drm_score": 0,
    "drm_triggers": "-",
    "lottery_ev": "-32.1%",
    "fvs_drm_verdict": "🔴严重",
    "vetoed": true,
    "veto_reason": "FVS-5,EV-32%",
    "old_correct": true,
    "new_correct": false
  },
  {
    "match": "法国 vs 波兰",
    "date": "2022-12-04",
    "stage": "round_of_16",
    "score": "3-1",
    "direction": "home",
    "actual": "home",
    "pinnacle_close": "1.40/4.95/9.50",
    "deVig": "69.9%/19.8%/10.3%",
    "fav_odds": "1.37",
    "fvs_score": 5,
    "fvs_triggers": "FVS-2(+2系统),FVS-3(+1),FVS-11(+2)",
    "drm_score": 0,
    "drm_triggers": "-",
    "lottery_ev": "-32.0%",
    "fvs_drm_verdict": "🔴严重",
    "vetoed": true,
    "veto_reason": "FVS-5,EV-32%",
    "old_correct": true,
    "new_correct": false
  },
  {
    "match": "英格兰 vs 塞内加尔",
    "date": "2022-12-05",
    "stage": "round_of_16",
    "score": "3-0",
    "direction": "home",
    "actual": "home",
    "pinnacle_close": "1.63/3.85/6.75",
    "deVig": "60.1%/25.4%/14.5%",
    "fav_odds": "1.58",
    "fvs_score": 1,
    "fvs_triggers": "FVS-7(+1)",
    "drm_score": 1,
    "drm_triggers": "DRM-1(+1)",
    "lottery_ev": "-32.7%",
    "fvs_drm_verdict": "正常",
    "vetoed": true,
    "veto_reason": "EV-33%",
    "old_correct": true,
    "new_correct": false
  },
  {
    "match": "日本 vs 克罗地亚",
    "date": "2022-12-05",
    "stage": "round_of_16",
    "score": "1-1",
    "direction": "away",
    "actual": "draw",
    "pinnacle_close": "3.89/3.33/2.16",
    "deVig": "25.2%/29.4%/45.4%",
    "fav_odds": "2.10",
    "fvs_score": 0,
    "fvs_triggers": "-",
    "drm_score": 2,
    "drm_triggers": "DRM-1(+2)",
    "lottery_ev": "-32.5%",
    "fvs_drm_verdict": "⚠️中平局",
    "vetoed": true,
    "veto_reason": "EV-32%",
    "old_correct": false,
    "new_correct": false
  },
  {
    "match": "摩洛哥 vs 西班牙",
    "date": "2022-12-06",
    "stage": "round_of_16",
    "score": "0-0",
    "direction": "away",
    "actual": "draw",
    "pinnacle_close": "6.25/3.90/1.66",
    "deVig": "15.7%/25.2%/59.1%",
    "fav_odds": "1.60",
    "fvs_score": 1,
    "fvs_triggers": "FVS-7(+1)",
    "drm_score": 1,
    "drm_triggers": "DRM-1(+1)",
    "lottery_ev": "-32.8%",
    "fvs_drm_verdict": "正常",
    "vetoed": true,
    "veto_reason": "EV-33%",
    "old_correct": false,
    "new_correct": false
  },
  {
    "match": "巴西 vs 韩国",
    "date": "2022-12-06",
    "stage": "round_of_16",
    "score": "4-1",
    "direction": "home",
    "actual": "home",
    "pinnacle_close": "1.25/6.60/13.00",
    "deVig": "77.8%/14.7%/7.5%",
    "fav_odds": "1.22",
    "fvs_score": 1,
    "fvs_triggers": "FVS-1(+1)",
    "drm_score": 0,
    "drm_triggers": "-",
    "lottery_ev": "-32.4%",
    "fvs_drm_verdict": "正常",
    "vetoed": true,
    "veto_reason": "EV-32%",
    "old_correct": true,
    "new_correct": false
  },
  {
    "match": "葡萄牙 vs 瑞士",
    "date": "2022-12-07",
    "stage": "round_of_16",
    "score": "6-1",
    "direction": "home",
    "actual": "home",
    "pinnacle_close": "2.02/3.60/4.01",
    "deVig": "48.4%/27.2%/24.4%",
    "fav_odds": "1.90",
    "fvs_score": 0,
    "fvs_triggers": "-",
    "drm_score": 1,
    "drm_triggers": "DRM-1(+1)",
    "lottery_ev": "-34.7%",
    "fvs_drm_verdict": "正常",
    "vetoed": true,
    "veto_reason": "EV-35%",
    "old_correct": true,
    "new_correct": false
  },
  {
    "match": "克罗地亚 vs 巴西",
    "date": "2022-12-09",
    "stage": "quarter",
    "score": "0-0",
    "direction": "away",
    "actual": "draw",
    "pinnacle_close": "9.00/4.85/1.41",
    "deVig": "10.8%/20.1%/69.1%",
    "fav_odds": "1.39",
    "fvs_score": 2,
    "fvs_triggers": "FVS-2(+2系统)",
    "drm_score": 2,
    "drm_triggers": "DRM-7(+2)",
    "lottery_ev": "-31.8%",
    "fvs_drm_verdict": "⚠️衰减",
    "vetoed": true,
    "veto_reason": "EV-32%,FVS+DRM双重",
    "old_correct": false,
    "new_correct": false
  },
  {
    "match": "荷兰 vs 阿根廷",
    "date": "2022-12-10",
    "stage": "quarter",
    "score": "2-2",
    "direction": "away",
    "actual": "draw",
    "pinnacle_close": "3.65/3.19/2.32",
    "deVig": "26.9%/30.8%/42.3%",
    "fav_odds": "2.21",
    "fvs_score": 0,
    "fvs_triggers": "-",
    "drm_score": 4,
    "drm_triggers": "DRM-1(+2),DRM-7(+2)",
    "lottery_ev": "-33.5%",
    "fvs_drm_verdict": "🔶高平局",
    "vetoed": true,
    "veto_reason": "EV-34%",
    "old_correct": false,
    "new_correct": false
  },
  {
    "match": "摩洛哥 vs 葡萄牙",
    "date": "2022-12-10",
    "stage": "quarter",
    "score": "1-0",
    "direction": "away",
    "actual": "home",
    "pinnacle_close": "6.69/3.96/1.59",
    "deVig": "14.5%/24.5%/61.0%",
    "fav_odds": "1.64",
    "fvs_score": 0,
    "fvs_triggers": "-",
    "drm_score": 2,
    "drm_triggers": "DRM-7(+2)",
    "lottery_ev": "-28.8%",
    "fvs_drm_verdict": "⚠️中平局",
    "vetoed": true,
    "veto_reason": "EV-29%",
    "old_correct": false,
    "new_correct": false
  },
  {
    "match": "英格兰 vs 法国",
    "date": "2022-12-11",
    "stage": "quarter",
    "score": "1-2",
    "direction": "away",
    "actual": "away",
    "pinnacle_close": "2.92/3.15/2.79",
    "deVig": "33.6%/31.2%/35.2%",
    "fav_odds": "2.67",
    "fvs_score": 0,
    "fvs_triggers": "-",
    "drm_score": 4,
    "drm_triggers": "DRM-1(+2),DRM-7(+2)",
    "lottery_ev": "-33.3%",
    "fvs_drm_verdict": "🔶高平局",
    "vetoed": true,
    "veto_reason": "EV-33%",
    "old_correct": true,
    "new_correct": false
  },
  {
    "match": "阿根廷 vs 克罗地亚",
    "date": "2022-12-14",
    "stage": "semi",
    "score": "3-0",
    "direction": "home",
    "actual": "home",
    "pinnacle_close": "2.04/3.09/4.86",
    "deVig": "48.1%/31.7%/20.2%",
    "fav_odds": "1.95",
    "fvs_score": 0,
    "fvs_triggers": "-",
    "drm_score": 4,
    "drm_triggers": "DRM-1(+2),DRM-7(+2)",
    "lottery_ev": "-33.5%",
    "fvs_drm_verdict": "🔶高平局",
    "vetoed": true,
    "veto_reason": "EV-34%",
    "old_correct": true,
    "new_correct": false
  },
  {
    "match": "法国 vs 摩洛哥",
    "date": "2022-12-15",
    "stage": "semi",
    "score": "2-0",
    "direction": "home",
    "actual": "home",
    "pinnacle_close": "1.64/3.80/6.74",
    "deVig": "59.7%/25.8%/14.5%",
    "fav_odds": "1.57",
    "fvs_score": 1,
    "fvs_triggers": "FVS-7(+1)",
    "drm_score": 3,
    "drm_triggers": "DRM-1(+1),DRM-7(+2)",
    "lottery_ev": "-33.3%",
    "fvs_drm_verdict": "⚠️中平局",
    "vetoed": true,
    "veto_reason": "EV-33%",
    "old_correct": true,
    "new_correct": false
  },
  {
    "match": "克罗地亚 vs 摩洛哥",
    "date": "2022-12-17",
    "stage": "third",
    "score": "2-1",
    "direction": "home",
    "actual": "home",
    "pinnacle_close": "2.31/3.66/3.16",
    "deVig": "42.3%/26.7%/30.9%",
    "fav_odds": "2.30",
    "fvs_score": 0,
    "fvs_triggers": "-",
    "drm_score": 1,
    "drm_triggers": "DRM-1(+1)",
    "lottery_ev": "-30.9%",
    "fvs_drm_verdict": "正常",
    "vetoed": true,
    "veto_reason": "EV-31%",
    "old_correct": true,
    "new_correct": false
  },
  {
    "match": "阿根廷 vs 法国",
    "date": "2022-12-18",
    "stage": "final",
    "score": "2-2",
    "direction": "home",
    "actual": "draw",
    "pinnacle_close": "2.67/3.20/3.04",
    "deVig": "36.9%/30.8%/32.4%",
    "fav_odds": "2.64",
    "fvs_score": 0,
    "fvs_triggers": "-",
    "drm_score": 4,
    "drm_triggers": "DRM-1(+2),DRM-7(+2)",
    "lottery_ev": "-30.9%",
    "fvs_drm_verdict": "🔶高平局",
    "vetoed": true,
    "veto_reason": "EV-31%",
    "old_correct": false,
    "new_correct": false
  }
]